openhkex/__init__.py
openhkex/parser/__init__.py
openhkex/web_request/__init__.py
openhkex-0.1.0.dist-info/LICENSE
openhkex-0.1.0.dist-info/METADATA
openhkex-0.1.0.dist-info/WHEEL
openhkex-0.1.0.dist-info/top_level.txt
openhkex-0.1.0.dist-info/RECORD
