Metadata-Version: 2.1
Name: openhkex
Version: 0.1.0
Summary: python library providing data service of Hong Kong Exchanges and Clearing Limited
Author-email: Louis Wan <chwanlouis@gmail.com>
License: GNU GENERAL PUBLIC LICENSE
Project-URL: Homepage, https://github.com/chwanlouis/openhkex
Classifier: Programming Language :: Python :: 3
Classifier: License :: OSI Approved :: GNU General Public License v3 (GPLv3)
Classifier: Operating System :: OS Independent
Requires-Python: >=3.6
License-File: LICENSE
